{"v":"4.8.0","meta":{"g":"LottieFiles AE 3.5.1","a":"","k":"","d":"","tc":""},"fr":24,"ip":0,"op":97,"w":872,"h":964,"nm":"LOTTIE EXPORT","ddd":0,"assets":[],"layers":[{"ddd":0,"ind":1,"ty":3,"nm":"Null 1","sr":1,"ks":{"o":{"a":0,"k":0,"ix":11},"r":{"a":1,"k":[{"i":{"x":[0.667],"y":[1]},"o":{"x":[0.333],"y":[0]},"t":14,"s":[0]},{"i":{"x":[0.667],"y":[1]},"o":{"x":[0.333],"y":[0]},"t":22,"s":[7.5]},{"i":{"x":[0.667],"y":[1]},"o":{"x":[0.333],"y":[0]},"t":29,"s":[7.5]},{"i":{"x":[0.667],"y":[1]},"o":{"x":[0.333],"y":[0]},"t":42,"s":[15]},{"i":{"x":[0.667],"y":[1]},"o":{"x":[0.333],"y":[0]},"t":49,"s":[15]},{"i":{"x":[0.667],"y":[1]},"o":{"x":[0.333],"y":[0]},"t":62,"s":[22.5]},{"i":{"x":[0.667],"y":[1]},"o":{"x":[0.333],"y":[0]},"t":69,"s":[22.5]},{"t":82,"s":[30]}],"ix":10},"p":{"a":1,"k":[{"i":{"x":0.667,"y":1},"o":{"x":0.333,"y":0},"t":14,"s":[499,602,0],"to":null,"ti":null},{"i":{"x":0.667,"y":0.667},"o":{"x":0.333,"y":0.333},"t":22,"s":[475,602,0],"to":null,"ti":null},{"i":{"x":0.667,"y":1},"o":{"x":0.333,"y":0},"t":29,"s":[475,602,0],"to":null,"ti":null},{"i":{"x":0.667,"y":0.667},"o":{"x":0.333,"y":0.333},"t":42,"s":[455,602,0],"to":null,"ti":null},{"i":{"x":0.667,"y":1},"o":{"x":0.333,"y":0},"t":49,"s":[455,602,0],"to":null,"ti":null},{"i":{"x":0.667,"y":0.667},"o":{"x":0.333,"y":0.333},"t":62,"s":[439.121,602,0],"to":null,"ti":null},{"i":{"x":0.667,"y":1},"o":{"x":0.333,"y":0},"t":69,"s":[439.121,602,0],"to":null,"ti":null},{"t":82,"s":[437,602,0]}],"ix":2},"a":{"a":0,"k":[27,-74,0],"ix":1},"s":{"a":0,"k":[100,100,100],"ix":6}},"ao":0,"ip":0,"op":97,"st":0,"bm":0,"completed":true},{"ddd":0,"ind":2,"ty":4,"nm":"LOGO Outlines","parent":1,"sr":1,"ks":{"o":{"a":0,"k":100,"ix":11},"r":{"a":1,"k":[{"i":{"x":[0.591],"y":[4.941]},"o":{"x":[0.566],"y":[0]},"t":9,"s":[0]},{"i":{"x":[0.275],"y":[1]},"o":{"x":[0.923],"y":[0.117]},"t":14,"s":[-3]},{"t":22,"s":[330]}],"ix":10},"p":{"a":0,"k":[26.988,-72.911,0],"ix":2},"a":{"a":0,"k":[129.008,375.132,0],"ix":1},"s":{"a":0,"k":[100,100,100],"ix":6}},"ao":0,"shapes":[{"ty":"gr","it":[{"ind":0,"ty":"sh","ix":1,"ks":{"a":0,"k":{"i":[[30.982,-91.931],[-57.393,15.745],[-5.522,15.745],[-31.998,91.931],[57.393,-15.745],[4.571,-15.745]],"o":[[30.982,-91.931],[-57.393,15.745],[-5.522,15.745],[-31.998,91.931],[57.393,-15.745],[4.571,-15.745]],"v":[[30.982,-91.931],[-57.393,15.745],[-5.522,15.745],[-31.998,91.931],[57.393,-15.745],[4.571,-15.745]],"c":true},"ix":2},"nm":"Path 1","mn":"ADBE Vector Shape - Group","hd":false,"_render":true},{"ty":"fl","c":{"a":0,"k":[0.945098099054,0.768627510819,0,1],"ix":4},"o":{"a":0,"k":100,"ix":5},"r":1,"bm":0,"nm":"Fill 1","mn":"ADBE Vector Graphic - Fill","hd":false,"_render":true},{"ty":"tr","p":{"a":0,"k":[128.501,169.133],"ix":2},"a":{"a":0,"k":[0,0],"ix":1},"s":{"a":0,"k":[100,100],"ix":3},"r":{"a":0,"k":0,"ix":6},"o":{"a":0,"k":100,"ix":7},"sk":{"a":0,"k":0,"ix":4},"sa":{"a":0,"k":0,"ix":5},"nm":"Transform","_render":true}],"nm":"Group 1","np":2,"cix":2,"bm":0,"ix":1,"mn":"ADBE Vector Group","hd":false,"_render":true},{"ty":"gr","it":[{"ind":0,"ty":"sh","ix":1,"ks":{"a":0,"k":{"i":[[73.837,128.5],[-55.903,128.5],[-88.376,113.96199999999999],[-88.376,-96.029],[-73.837,-128.5],[55.904,-128.5],[88.376,-113.96199999999999],[88.376,96.029]],"o":[[55.904,128.5],[-73.837,128.5],[-88.376,96.029],[-88.376,-113.96199999999999],[-55.903,-128.5],[73.837,-128.5],[88.376,-96.029],[88.376,113.96199999999999]],"v":[[55.904,128.5],[-55.903,128.5],[-88.376,96.029],[-88.376,-96.029],[-55.903,-128.5],[55.904,-128.5],[88.376,-96.029],[88.376,96.029]],"c":true},"ix":2},"nm":"Path 1","mn":"ADBE Vector Shape - Group","hd":false,"_render":true},{"ty":"st","c":{"a":0,"k":[0.945098099054,0.768627510819,0,1],"ix":3},"o":{"a":0,"k":100,"ix":4},"w":{"a":0,"k":16.253,"ix":5},"lc":1,"lj":1,"ml":10,"bm":0,"nm":"Stroke 1","mn":"ADBE Vector Graphic - Stroke","hd":false,"_render":true},{"ty":"fl","c":{"a":0,"k":[0.035294117647,0.125490196078,0.188235309077,1],"ix":4},"o":{"a":0,"k":100,"ix":5},"r":1,"bm":0,"nm":"Fill 1","mn":"ADBE Vector Graphic - Fill","hd":false,"_render":true},{"ty":"tr","p":{"a":0,"k":[129.008,169.132],"ix":2},"a":{"a":0,"k":[0,0],"ix":1},"s":{"a":0,"k":[100,100],"ix":3},"r":{"a":0,"k":0,"ix":6},"o":{"a":0,"k":100,"ix":7},"sk":{"a":0,"k":0,"ix":4},"sa":{"a":0,"k":0,"ix":5},"nm":"Transform","_render":true}],"nm":"Group 2","np":3,"cix":2,"bm":0,"ix":2,"mn":"ADBE Vector Group","hd":false,"_render":true}],"ip":0,"op":19,"st":0,"bm":0,"completed":true},{"ddd":0,"ind":3,"ty":4,"nm":"3 Outlines","parent":1,"sr":1,"ks":{"o":{"a":0,"k":100,"ix":11},"r":{"a":1,"k":[{"i":{"x":[0.591],"y":[4.941]},"o":{"x":[0.566],"y":[0]},"t":29,"s":[0]},{"i":{"x":[0.347],"y":[1]},"o":{"x":[0.923],"y":[0.115]},"t":34,"s":[-3]},{"t":42,"s":[337.5]}],"ix":10},"p":{"a":0,"k":[27,-72.539,0],"ix":2},"a":{"a":0,"k":[169.888,382.289,0],"ix":1},"s":{"a":0,"k":[100,100,100],"ix":6}},"ao":0,"shapes":[{"ty":"gr","it":[{"ind":0,"ty":"sh","ix":1,"ks":{"a":0,"k":{"i":[[17.269,-19.137],[17.624,-11.064],[14.306000000000001,-3.6959999999999997],[16.505000000000003,1.843],[20.912000000000003,8.534],[21.491,16.848],[19.047,24.535],[14.152000000000001,30.527],[7.245,34.161],[-0.7719999999999998,34.669],[-8.035,31.943],[-13.733,26.61],[-17.27,19.197999999999997],[-3.483,14.436],[-2.519,17.718],[1.253,20.536],[5.278,19.338],[7.321,14.784],[6.7,11.164000000000001],[5.372,8.348],[3.557,6.143999999999999],[1.4220000000000002,4.986000000000001],[-0.6,-4.525],[0.8079999999999999,-5.027],[2.3499999999999996,-7.294],[3.3030000000000004,-10.277],[3.596,-13.514],[2.513,-17.761],[-1.2009999999999998,-20.548000000000002],[-5.235,-19.36],[-7.342,-14.873000000000001],[-21.269,-11.182],[-21.491,-16.755],[-19.043,-24.443],[-14.151,-30.454],[-7.258000000000001,-34.161],[0.7650000000000001,-34.658],[8.034,-31.854000000000003],[13.733,-26.518]],"o":[[17.99,-13.661],[15.475,-5.981],[14.786999999999999,-0.04200000000000004],[19.889000000000003,6.14],[21.642000000000003,14.076],[20.14,22.151],[16.016,28.776],[9.711,33.289],[1.831,34.874],[-5.776999999999999,33.150999999999996],[-12.056000000000001,28.629],[-16.41,21.837],[-17.651,16.301],[-3.246,16.234],[-0.06999999999999984,20.05],[4.122999999999999,20.158],[7.0089999999999995,16.424],[6.966,12.087],[5.87,9.225000000000001],[4.203,6.778],[2.151,5.178999999999999],[0.665,5.086],[0.15700000000000003,-4.625],[1.899,-6.449],[3.056,-9.24],[3.5860000000000003,-12.488],[3.233,-16.273],[0.11399999999999988,-20.065],[-4.071,-20.17],[-7.016,-16.499],[-7.101,-13.047],[-21.642,-14.014],[-20.141000000000002,-22.058],[-16.017,-28.688000000000002],[-9.718,-33.278],[-1.8430000000000004,-34.874],[5.7780000000000005,-33.078],[12.06,-28.537000000000003],[16.41,-21.744999999999997]],"v":[[17.642,-16.305],[16.552,-8.523],[13.032,-1.671],[18.199,3.989],[21.26,11.178],[20.815,19.497],[17.532,26.657],[11.929,31.91],[4.54,34.517],[-3.272,33.912],[-10.044,30.288],[-15.068,24.221],[-17.651,16.301],[-3.483,14.436],[-1.295,18.882],[2.675,20.349],[6.145,17.879],[7.082,12.967],[6.287,10.194],[4.787,7.561],[2.856,5.661],[0.665,5.086],[-0.6,-4.525],[1.355,-5.74],[2.703,-8.267],[3.446,-11.383],[3.472,-14.455],[1.313,-18.913],[-2.638,-20.359],[-6.126,-17.93],[-7.101,-13.047],[-21.269,-11.182],[-20.812,-19.409],[-17.528,-26.565],[-11.932,-31.864],[-4.549,-34.517],[3.27,-33.866],[10.047,-30.196],[15.071,-24.133]],"c":true},"ix":2},"nm":"Path 1","mn":"ADBE Vector Shape - Group","hd":false,"_render":true},{"ty":"fl","c":{"a":0,"k":[0.945098099054,0.768627510819,0,1],"ix":4},"o":{"a":0,"k":100,"ix":5},"r":1,"bm":0,"nm":"Fill 1","mn":"ADBE Vector Graphic - Fill","hd":false,"_render":true},{"ty":"tr","p":{"a":0,"k":[143.126,175.851],"ix":2},"a":{"a":0,"k":[0,0],"ix":1},"s":{"a":0,"k":[100,100],"ix":3},"r":{"a":0,"k":0,"ix":6},"o":{"a":0,"k":100,"ix":7},"sk":{"a":0,"k":0,"ix":4},"sa":{"a":0,"k":0,"ix":5},"nm":"Transform","_render":true}],"nm":"Group 1","np":2,"cix":2,"bm":0,"ix":1,"mn":"ADBE Vector Group","hd":false,"_render":true},{"ty":"gr","it":[{"ind":0,"ty":"sh","ix":1,"ks":{"a":0,"k":{"i":[[89.978,117.762],[-38.654,134.697],[-72.745,124.522],[-100.154,-83.673],[-89.979,-117.764],[38.654,-134.698],[72.745,-124.523],[100.154,83.671]],"o":[[72.198,120.103],[-56.434000000000005,137.038],[-75.086,106.742],[-102.49499999999999,-101.453],[-72.199,-120.104],[56.434000000000005,-137.03900000000002],[75.086,-106.743],[102.49499999999999,101.45100000000001]],"v":[[72.198,120.103],[-38.654,134.697],[-75.086,106.742],[-100.154,-83.673],[-72.199,-120.104],[38.654,-134.698],[75.086,-106.743],[100.154,83.671]],"c":true},"ix":2},"nm":"Path 1","mn":"ADBE Vector Shape - Group","hd":false,"_render":true},{"ty":"st","c":{"a":0,"k":[0.945098099054,0.768627510819,0,1],"ix":3},"o":{"a":0,"k":100,"ix":4},"w":{"a":0,"k":16.253,"ix":5},"lc":1,"lj":1,"ml":10,"bm":0,"nm":"Stroke 1","mn":"ADBE Vector Graphic - Stroke","hd":false,"_render":true},{"ty":"fl","c":{"a":0,"k":[0.035294117647,0.125490196078,0.188235309077,1],"ix":4},"o":{"a":0,"k":100,"ix":5},"r":1,"bm":0,"nm":"Fill 1","mn":"ADBE Vector Graphic - Fill","hd":false,"_render":true},{"ty":"tr","p":{"a":0,"k":[143.127,177.671],"ix":2},"a":{"a":0,"k":[0,0],"ix":1},"s":{"a":0,"k":[100,100],"ix":3},"r":{"a":0,"k":0,"ix":6},"o":{"a":0,"k":100,"ix":7},"sk":{"a":0,"k":0,"ix":4},"sa":{"a":0,"k":0,"ix":5},"nm":"Transform","_render":true}],"nm":"Group 2","np":3,"cix":2,"bm":0,"ix":2,"mn":"ADBE Vector Group","hd":false,"_render":true}],"ip":0,"op":39,"st":0,"bm":0,"completed":true},{"ddd":0,"ind":4,"ty":4,"nm":"2 Outlines","parent":1,"sr":1,"ks":{"o":{"a":0,"k":100,"ix":11},"r":{"a":1,"k":[{"i":{"x":[0.591],"y":[4.941]},"o":{"x":[0.566],"y":[0]},"t":49,"s":[0]},{"i":{"x":[0.347],"y":[1]},"o":{"x":[0.923],"y":[0.112]},"t":54,"s":[-3]},{"t":62,"s":[345]}],"ix":10},"p":{"a":0,"k":[27.286,-73.203,0],"ix":2},"a":{"a":0,"k":[208.831,382.589,0],"ix":1},"s":{"a":0,"k":[100,100,100],"ix":6}},"ao":0,"shapes":[{"ty":"gr","it":[{"ind":0,"ty":"sh","ix":1,"ks":{"a":0,"k":{"i":[[0.748,16.528],[23.775,10.358],[27.553,24.459],[-19.067,36.95],[-22.845,22.85],[-22.562,22.774],[0.401,-6.948],[1.7939999999999998,-9.322],[2.2199999999999998,-13.683],[1.009,-17.453000000000003],[-1.068,-20.171],[-3.7049999999999996,-21.797],[-6.599,-22.198],[-9.450999999999999,-21.200000000000003],[-11.481,-19.061999999999998],[-12.634,-16.08],[-12.694,-12.572],[-12.199,-10.725],[-26.095,-6.198],[-26.472,-7.605],[-27.552999999999997,-13.828999999999999],[-25.964,-22.752],[-21.382,-30.157],[-14.366999999999999,-35.230000000000004],[-5.56,-36.949999999999996],[2.9110000000000005,-34.924],[10.07,-29.820999999999998],[15.078999999999999,-22.096],[17.066,-11.483],[14.096,-0.8130000000000002]],"o":[[0.748,16.528],[23.775,10.358],[27.553,24.459],[-19.067,36.95],[-22.845,22.85],[-22.562,22.774],[1.246,-8.048],[2.296,-12.206999999999999],[1.4989999999999999,-16.375],[-0.30700000000000005,-19.383000000000003],[-2.796,-21.389000000000003],[-5.622999999999999,-22.226],[-8.588000000000001,-21.665],[-10.895,-19.871000000000002],[-12.365,-17.144],[-12.809000000000001,-13.75],[-12.375,-11.383],[-12.199,-10.725],[-26.095,-6.198],[-27.311,-10.738],[-26.836,-19.932],[-23.187,-27.930999999999997],[-16.945,-33.899],[-8.472999999999999,-36.809000000000005],[0.2190000000000003,-35.945],[7.901,-31.825999999999997],[13.739,-24.893],[16.925,-15.203999999999999],[15.615,-4.11],[11.787,2.089]],"v":[[0.748,16.528],[23.775,10.358],[27.553,24.459],[-19.067,36.95],[-22.845,22.85],[-22.562,22.774],[0.401,-6.948],[2.046,-10.767],[1.817,-15.186],[0.352,-18.42],[-1.932,-20.78],[-4.664,-22.012],[-7.594,-21.932],[-10.171,-20.536],[-11.921,-18.104],[-12.72,-14.918],[-12.375,-11.383],[-12.199,-10.725],[-26.095,-6.198],[-26.472,-7.605],[-27.194,-16.88],[-24.576,-25.342],[-19.166,-32.03],[-11.418,-36.02],[-2.671,-36.449],[5.408,-33.376],[11.906,-27.357],[15.918,-18.964],[16.34,-7.796],[11.787,2.089]],"c":true},"ix":2},"nm":"Path 1","mn":"ADBE Vector Shape - Group","hd":false,"_render":true},{"ty":"fl","c":{"a":0,"k":[0.945098099054,0.768627510819,0,1],"ix":4},"o":{"a":0,"k":100,"ix":5},"r":1,"bm":0,"nm":"Fill 1","mn":"ADBE Vector Graphic - Fill","hd":false,"_render":true},{"ty":"tr","p":{"a":0,"k":[155.393,183.76],"ix":2},"a":{"a":0,"k":[0,0],"ix":1},"s":{"a":0,"k":[100,100],"ix":3},"r":{"a":0,"k":0,"ix":6},"o":{"a":0,"k":100,"ix":7},"sk":{"a":0,"k":0,"ix":4},"sa":{"a":0,"k":0,"ix":5},"nm":"Transform","_render":true}],"nm":"Group 1","np":2,"cix":2,"bm":0,"ix":1,"mn":"ADBE Vector Group","hd":false,"_render":true},{"ty":"gr","it":[{"ind":0,"ty":"sh","ix":1,"ks":{"a":0,"k":{"i":[[104.57900000000001,105.01],[-20.742,138.59],[-55.869,132.952],[-110.219,-69.884],[-104.58,-105.01100000000001],[20.742,-138.591],[55.867999999999995,-132.953],[110.219,69.883]],"o":[[87.257,109.652],[-38.064,143.232],[-60.511,115.629],[-114.86,-87.206],[-87.258,-109.653],[38.064,-143.232],[60.51,-115.63],[114.86,87.205]],"v":[[87.257,109.652],[-20.742,138.59],[-60.511,115.629],[-110.219,-69.884],[-87.258,-109.653],[20.742,-138.591],[60.51,-115.63],[110.219,69.883]],"c":true},"ix":2},"nm":"Path 1","mn":"ADBE Vector Shape - Group","hd":false,"_render":true},{"ty":"st","c":{"a":0,"k":[0.945098099054,0.768627510819,0,1],"ix":3},"o":{"a":0,"k":100,"ix":4},"w":{"a":0,"k":16.253,"ix":5},"lc":1,"lj":1,"ml":10,"bm":0,"nm":"Stroke 1","mn":"ADBE Vector Graphic - Stroke","hd":false,"_render":true},{"ty":"fl","c":{"a":0,"k":[0.035294117647,0.125490196078,0.188235309077,1],"ix":4},"o":{"a":0,"k":100,"ix":5},"r":1,"bm":0,"nm":"Fill 1","mn":"ADBE Vector Graphic - Fill","hd":false,"_render":true},{"ty":"tr","p":{"a":0,"k":[155.492,183.864],"ix":2},"a":{"a":0,"k":[0,0],"ix":1},"s":{"a":0,"k":[100,100],"ix":3},"r":{"a":0,"k":0,"ix":6},"o":{"a":0,"k":100,"ix":7},"sk":{"a":0,"k":0,"ix":4},"sa":{"a":0,"k":0,"ix":5},"nm":"Transform","_render":true}],"nm":"Group 2","np":3,"cix":2,"bm":0,"ix":2,"mn":"ADBE Vector Group","hd":false,"_render":true}],"ip":0,"op":59,"st":0,"bm":0,"completed":true},{"ddd":0,"ind":5,"ty":4,"nm":"1 Outlines","parent":1,"sr":1,"ks":{"o":{"a":0,"k":100,"ix":11},"r":{"a":1,"k":[{"i":{"x":[0.591],"y":[4.941]},"o":{"x":[0.566],"y":[0]},"t":69,"s":[0]},{"i":{"x":[0.347],"y":[1]},"o":{"x":[0.923],"y":[0.11]},"t":74,"s":[-3]},{"t":82,"s":[352.5]}],"ix":10},"p":{"a":0,"k":[27.351,-73.025,0],"ix":2},"a":{"a":0,"k":[244.682,377.894,0],"ix":1},"s":{"a":0,"k":[100,100,100],"ix":6}},"ao":0,"shapes":[{"ty":"gr","it":[{"ind":0,"ty":"sh","ix":1,"ks":{"a":0,"k":{"i":[[0.855,-35.183],[27.678,29.573],[14.132,35.183],[-6.667,-15.031],[-17.745,-4.729],[-27.678,-15.429],[-12.652,-29.48],[-12.69,-29.572]],"o":[[0.855,-35.183],[27.678,29.573],[14.132,35.183],[-6.667,-15.031],[-17.745,-4.729],[-27.678,-15.429],[-12.652,-29.48],[-12.69,-29.572]],"v":[[0.855,-35.183],[27.678,29.573],[14.132,35.183],[-6.667,-15.031],[-17.745,-4.729],[-27.678,-15.429],[-12.652,-29.48],[-12.69,-29.572]],"c":true},"ix":2},"nm":"Path 1","mn":"ADBE Vector Shape - Group","hd":false,"_render":true},{"ty":"fl","c":{"a":0,"k":[0.945098099054,0.768627510819,0,1],"ix":4},"o":{"a":0,"k":100,"ix":5},"r":1,"bm":0,"nm":"Fill 1","mn":"ADBE Vector Graphic - Fill","hd":false,"_render":true},{"ty":"tr","p":{"a":0,"k":[161.64,187.607],"ix":2},"a":{"a":0,"k":[0,0],"ix":1},"s":{"a":0,"k":[100,100],"ix":3},"r":{"a":0,"k":0,"ix":6},"o":{"a":0,"k":100,"ix":7},"sk":{"a":0,"k":0,"ix":4},"sa":{"a":0,"k":0,"ix":5},"nm":"Transform","_render":true}],"nm":"Group 1","np":2,"cix":2,"bm":0,"ix":1,"mn":"ADBE Vector Group","hd":false,"_render":true},{"ty":"gr","it":[{"ind":0,"ty":"sh","ix":1,"ks":{"a":0,"k":{"i":[[117.392,90.462],[-2.473,140.112],[-38.037,139.107],[-118.396,-54.899],[-117.39099999999999,-90.462],[2.474,-140.112],[38.037,-139.107],[118.397,54.899]],"o":[[100.824,97.325],[-19.041999999999998,146.975],[-44.9,122.539],[-125.259,-71.467],[-100.823,-97.325],[19.043,-146.975],[44.9,-122.539],[125.26,71.467]],"v":[[100.824,97.325],[-2.473,140.112],[-44.9,122.539],[-118.396,-54.899],[-100.823,-97.325],[2.474,-140.112],[44.9,-122.539],[118.397,54.899]],"c":true},"ix":2},"nm":"Path 1","mn":"ADBE Vector Shape - Group","hd":false,"_render":true},{"ty":"st","c":{"a":0,"k":[0.945098099054,0.768627510819,0,1],"ix":3},"o":{"a":0,"k":100,"ix":4},"w":{"a":0,"k":16.253,"ix":5},"lc":1,"lj":1,"ml":10,"bm":0,"nm":"Stroke 1","mn":"ADBE Vector Graphic - Stroke","hd":false,"_render":true},{"ty":"fl","c":{"a":0,"k":[0.035294117647,0.125490196078,0.188235309077,1],"ix":4},"o":{"a":0,"k":100,"ix":5},"r":1,"bm":0,"nm":"Fill 1","mn":"ADBE Vector Graphic - Fill","hd":false,"_render":true},{"ty":"tr","p":{"a":0,"k":[165.892,187.607],"ix":2},"a":{"a":0,"k":[0,0],"ix":1},"s":{"a":0,"k":[100,100],"ix":3},"r":{"a":0,"k":0,"ix":6},"o":{"a":0,"k":100,"ix":7},"sk":{"a":0,"k":0,"ix":4},"sa":{"a":0,"k":0,"ix":5},"nm":"Transform","_render":true}],"nm":"Group 2","np":3,"cix":2,"bm":0,"ix":2,"mn":"ADBE Vector Group","hd":false,"_render":true}],"ip":0,"op":79,"st":0,"bm":0,"completed":true},{"ddd":0,"ind":6,"ty":4,"nm":"GO Outlines","parent":1,"sr":1,"ks":{"o":{"a":0,"k":100,"ix":11},"r":{"a":0,"k":0,"ix":10},"p":{"a":0,"k":[-66.134,-237.313,0],"ix":2},"a":{"a":0,"k":[183.496,202.978,0],"ix":1},"s":{"a":1,"k":[{"i":{"x":[0.667,0.667,0.667],"y":[1,1,1]},"o":{"x":[0.333,0.333,0.333],"y":[0,0,0]},"t":81,"s":[100,100,100]},{"i":{"x":[0.833,0.833,0.833],"y":[1,1,1]},"o":{"x":[0.167,0.167,0.167],"y":[0,0,0]},"t":88,"s":[125,125,100]},{"t":95,"s":[120,120,100]}],"ix":6}},"ao":0,"shapes":[{"ty":"gr","it":[{"ind":0,"ty":"sh","ix":1,"ks":{"a":0,"k":{"i":[[7.935,23.846],[2.882,15.095],[11.631,10.044],[16.684,18.795]],"o":[[7.935,23.846],[2.882,15.095],[11.631,10.044],[16.684,18.795]],"v":[[7.935,23.846],[2.882,15.095],[11.631,10.044],[16.684,18.795]],"c":true},"ix":2},"nm":"Path 1","mn":"ADBE Vector Shape - Group","hd":false,"_render":true},{"ind":1,"ty":"sh","ix":2,"ks":{"a":0,"k":{"i":[[-16.684,-18.795],[-7.935,-23.846],[9.341,6.077],[0.593,11.129]],"o":[[-16.684,-18.795],[-7.935,-23.846],[9.341,6.077],[0.593,11.129]],"v":[[-16.684,-18.795],[-7.935,-23.846],[9.341,6.077],[0.593,11.129]],"c":true},"ix":2},"nm":"Path 2","mn":"ADBE Vector Shape - Group","hd":false,"_render":true},{"ty":"mm","mm":1,"nm":"Merge Paths 1","mn":"ADBE Vector Filter - Merge","hd":false,"_render":true},{"ty":"fl","c":{"a":0,"k":[0.945098099054,0.768627510819,0,1],"ix":4},"o":{"a":0,"k":100,"ix":5},"r":1,"bm":0,"nm":"Fill 1","mn":"ADBE Vector Graphic - Fill","hd":false,"_render":true},{"ty":"tr","p":{"a":0,"k":[218.446,165.39],"ix":2},"a":{"a":0,"k":[0,0],"ix":1},"s":{"a":0,"k":[100,100],"ix":3},"r":{"a":0,"k":0,"ix":6},"o":{"a":0,"k":100,"ix":7},"sk":{"a":0,"k":0,"ix":4},"sa":{"a":0,"k":0,"ix":5},"nm":"Transform","_render":true}],"nm":"Group 1","np":4,"cix":2,"bm":0,"ix":1,"mn":"ADBE Vector Group","hd":false,"_render":true},{"ty":"gr","it":[{"ind":0,"ty":"sh","ix":1,"ks":{"a":0,"k":{"i":[[-5.532,-13.008000000000001],[-9.634,-10.213000000000001],[-12.07,-5.948],[-12.728000000000002,-0.9540000000000001],[-11.496,4.426],[-8.383,9.171],[-4.053,12.323],[0.7430000000000001,13.668],[5.601999999999999,12.995999999999999],[9.681999999999999,10.213000000000001],[12.125,5.932],[12.798,0.876],[11.545,-4.43],[8.436,-9.189],[4.125,-12.403],[-0.6920000000000002,-13.668999999999999]],"o":[[-8.442,-11.328],[-11.454,-7.456],[-12.715,-2.6800000000000006],[-12.128,2.684],[-9.57,7.760999999999999],[-5.555,11.472],[-0.8769999999999998,13.439],[4.04,13.471],[8.512,11.315999999999999],[11.504,7.455000000000001],[12.787,2.6000000000000005],[12.181000000000001,-2.702],[9.619,-7.765000000000001],[5.624,-11.55],[0.9320000000000002,-13.455],[-3.992,-13.469999999999999]],"v":[[-6.968,-12.179],[-10.544,-8.836],[-12.394,-4.315],[-12.428,0.866],[-10.532,6.095],[-6.968,10.322],[-2.465,12.881],[2.391,13.568],[7.076,12.145],[10.594,8.832],[12.455,4.267],[12.49,-0.912],[10.583,-6.096],[7.031,-10.368],[2.527,-12.929],[-2.341,-13.572]],"c":true},"ix":2},"nm":"Path 1","mn":"ADBE Vector Shape - Group","hd":false,"_render":true},{"ind":1,"ty":"sh","ix":2,"ks":{"a":0,"k":{"i":[[14.742,19.384],[6.646000000000001,23.346],[-2.306,23.578],[-10.951,20.192],[-17.673,13.936],[-21.943,5.461],[-22.88,-3.6159999999999997],[-20.354999999999997,-12.552],[-14.693,-19.387],[-6.596,-23.347],[2.356,-23.579],[10.950000000000001,-20.166],[17.733999999999998,-13.921],[21.983,-5.459],[22.891,3.6339999999999995],[20.403,12.552]],"o":[[9.454,22.437],[0.7050000000000001,23.925],[-8.298,21.641],[-15.690000000000001,16.291999999999998],[-20.884,8.375],[-22.951,-0.593],[-21.559,-9.770999999999999],[-16.883,-17.408],[-9.405,-22.44],[-0.6569999999999996,-23.925],[8.309,-21.623],[15.73,-16.289],[20.944,-8.36],[22.951,0.6190000000000002],[21.61,9.77],[16.933,17.407]],"v":[[12.098,20.911],[3.676,23.634],[-5.365,22.593],[-13.32,18.243],[-19.267,11.176],[-22.446,2.435],[-22.238,-6.632],[-18.618,-14.982],[-12.049,-20.914],[-3.627,-23.637],[5.414,-22.597],[13.342,-18.227],[19.351,-11.12],[22.469,-2.42],[22.287,6.629],[18.668,14.978]],"c":true},"ix":2},"nm":"Path 2","mn":"ADBE Vector Shape - Group","hd":false,"_render":true},{"ty":"mm","mm":1,"nm":"Merge Paths 1","mn":"ADBE Vector Filter - Merge","hd":false,"_render":true},{"ty":"fl","c":{"a":0,"k":[0.945098099054,0.768627510819,0,1],"ix":4},"o":{"a":0,"k":100,"ix":5},"r":1,"bm":0,"nm":"Fill 1","mn":"ADBE Vector Graphic - Fill","hd":false,"_render":true},{"ty":"tr","p":{"a":0,"k":[187.68,187.825],"ix":2},"a":{"a":0,"k":[0,0],"ix":1},"s":{"a":0,"k":[100,100],"ix":3},"r":{"a":0,"k":0,"ix":6},"o":{"a":0,"k":100,"ix":7},"sk":{"a":0,"k":0,"ix":4},"sa":{"a":0,"k":0,"ix":5},"nm":"Transform","_render":true}],"nm":"Group 2","np":4,"cix":2,"bm":0,"ix":2,"mn":"ADBE Vector Group","hd":false,"_render":true},{"ty":"gr","it":[{"ind":0,"ty":"sh","ix":1,"ks":{"a":0,"k":{"i":[[21.566,-6.519],[22.813,-1.1470000000000002],[22.52,6.358999999999999],[19.706999999999997,13.701],[14.419,19.539],[6.672000000000001,23.299],[-2.261,23.520000000000003],[-10.874,20.119],[-17.646,13.892],[-21.907,5.409],[-22.796,-3.6950000000000003],[-20.326,-12.600000000000001],[-14.667,-19.434],[-5.893,-23.591],[4.237,-23.243],[3.539,-12.599],[-0.07000000000000006,-13.731],[-5.416,-13.107],[-9.633,-10.244],[-12.040000000000001,-5.991],[-12.738,-0.958],[-11.455,4.406],[-8.345,9.168],[-4.048,12.339],[0.7699999999999998,13.614],[5.594,12.969],[9.998,9.907],[12.488999999999999,4.968999999999999],[2.914,8.683],[-2.138,-0.068],[13.845,-9.296],[14.137,-9.465],[14.43,-9.633],[18.512,-11.99],[21.107,-7.497]],"o":[[22.403,-3.6320000000000006],[22.875,3.9],[20.951,11.363],[16.395,17.841],[9.48,22.39],[0.7330000000000001,23.877],[-8.214,21.564],[-15.654,16.242],[-20.858,8.329],[-22.875,-0.669],[-21.514,-9.828],[-16.855999999999998,-17.454],[-9.068,-22.667],[0.8889999999999998,-23.877000000000002],[7.542,-21.831],[1.739,-13.377],[-3.724,-13.59],[-8.45,-11.355],[-11.42,-7.501],[-12.726,-2.69],[-12.1,2.6639999999999997],[-9.524000000000001,7.75],[-5.548,11.495999999999999],[-0.8459999999999999,13.396],[4.039,13.439],[8.706,11.172],[11.901,6.736000000000001],[12.715,3.025],[2.914,8.683],[-2.138,-0.068],[13.845,-9.296],[14.137,-9.465],[14.43,-9.633],[18.512,-11.99],[21.398,-6.991]],"v":[[21.613,-6.081],[22.845,1.376],[21.779,8.758],[18.051,15.771],[12.124,20.864],[3.702,23.587],[-5.28,22.513],[-13.263,18.178],[-19.241,11.129],[-22.389,2.371],[-22.151,-6.711],[-18.592,-15.028],[-12.023,-20.96],[-2.5,-23.734],[7.542,-21.831],[3.539,-12.599],[-1.897,-13.661],[-6.971,-12.209],[-10.526,-8.874],[-12.384,-4.34],[-12.418,0.851],[-10.49,6.077],[-6.945,10.331],[-2.449,12.868],[2.405,13.525],[7.073,12.115],[10.949,8.32],[12.715,3.025],[2.914,8.683],[-2.138,-0.068],[13.845,-9.296],[14.137,-9.465],[14.43,-9.633],[18.512,-11.99],[21.107,-7.497]],"c":true},"ix":2},"nm":"Path 1","mn":"ADBE Vector Shape - Group","hd":false,"_render":true},{"ty":"fl","c":{"a":0,"k":[0.945098099054,0.768627510819,0,1],"ix":4},"o":{"a":0,"k":100,"ix":5},"r":1,"bm":0,"nm":"Fill 1","mn":"ADBE Vector Graphic - Fill","hd":false,"_render":true},{"ty":"tr","p":{"a":0,"k":[144.67,212.843],"ix":2},"a":{"a":0,"k":[0,0],"ix":1},"s":{"a":0,"k":[100,100],"ix":3},"r":{"a":0,"k":0,"ix":6},"o":{"a":0,"k":100,"ix":7},"sk":{"a":0,"k":0,"ix":4},"sa":{"a":0,"k":0,"ix":5},"nm":"Transform","_render":true}],"nm":"Group 3","np":2,"cix":2,"bm":0,"ix":3,"mn":"ADBE Vector Group","hd":false,"_render":true},{"ty":"gr","it":[{"ind":0,"ty":"sh","ix":1,"ks":{"a":0,"k":{"i":[[128.196,74.365],[15.836,139.236],[-19.554000000000002,142.882],[-124.549,-38.976],[-128.195,-74.366],[-15.835,-139.237],[19.554000000000002,-142.882],[124.55,38.975]],"o":[[112.665,83.332],[0.3049999999999997,148.203],[-28.52,127.351],[-133.51600000000002,-54.507],[-112.664,-83.332],[-0.30400000000000027,-148.203],[28.521,-127.351],[133.517,54.506]],"v":[[112.665,83.332],[15.836,139.236],[-28.52,127.351],[-124.549,-38.976],[-112.664,-83.332],[-15.835,-139.237],[28.521,-127.351],[124.55,38.975]],"c":true},"ix":2},"nm":"Path 1","mn":"ADBE Vector Shape - Group","hd":false,"_render":true},{"ty":"st","c":{"a":0,"k":[0.945098099054,0.768627510819,0,1],"ix":3},"o":{"a":0,"k":100,"ix":4},"w":{"a":0,"k":16.253,"ix":5},"lc":1,"lj":1,"ml":10,"bm":0,"nm":"Stroke 1","mn":"ADBE Vector Graphic - Stroke","hd":false,"_render":true},{"ty":"fl","c":{"a":0,"k":[0.035294117647,0.125490196078,0.188235309077,1],"ix":4},"o":{"a":0,"k":100,"ix":5},"r":1,"bm":0,"nm":"Fill 1","mn":"ADBE Vector Graphic - Fill","hd":false,"_render":true},{"ty":"tr","p":{"a":0,"k":[174.149,188.835],"ix":2},"a":{"a":0,"k":[0,0],"ix":1},"s":{"a":0,"k":[100,100],"ix":3},"r":{"a":0,"k":0,"ix":6},"o":{"a":0,"k":100,"ix":7},"sk":{"a":0,"k":0,"ix":4},"sa":{"a":0,"k":0,"ix":5},"nm":"Transform","_render":true}],"nm":"Group 4","np":3,"cix":2,"bm":0,"ix":4,"mn":"ADBE Vector Group","hd":false,"_render":true}],"ip":0,"op":97,"st":0,"bm":0,"completed":true},{"ddd":0,"ind":7,"ty":4,"nm":"LOGO Outlines 2","parent":1,"sr":1,"ks":{"o":{"a":0,"k":100,"ix":11},"r":{"a":1,"k":[{"i":{"x":[0.591],"y":[4.941]},"o":{"x":[0.566],"y":[0]},"t":9,"s":[0]},{"i":{"x":[0.275],"y":[1]},"o":{"x":[0.923],"y":[0.117]},"t":14,"s":[-3]},{"t":22,"s":[330]}],"ix":10},"p":{"a":0,"k":[26.988,-72.911,0],"ix":2},"a":{"a":0,"k":[129.008,375.132,0],"ix":1},"s":{"a":0,"k":[100,100,100],"ix":6}},"ao":0,"shapes":[{"ty":"gr","it":[{"ind":0,"ty":"sh","ix":1,"ks":{"a":0,"k":{"i":[[30.982,-91.931],[-57.393,15.745],[-5.522,15.745],[-31.998,91.931],[57.393,-15.745],[4.571,-15.745]],"o":[[30.982,-91.931],[-57.393,15.745],[-5.522,15.745],[-31.998,91.931],[57.393,-15.745],[4.571,-15.745]],"v":[[30.982,-91.931],[-57.393,15.745],[-5.522,15.745],[-31.998,91.931],[57.393,-15.745],[4.571,-15.745]],"c":true},"ix":2},"nm":"Path 1","mn":"ADBE Vector Shape - Group","hd":false,"_render":true},{"ty":"fl","c":{"a":0,"k":[0.945098099054,0.768627510819,0,1],"ix":4},"o":{"a":0,"k":100,"ix":5},"r":1,"bm":0,"nm":"Fill 1","mn":"ADBE Vector Graphic - Fill","hd":false,"_render":true},{"ty":"tr","p":{"a":0,"k":[128.501,169.133],"ix":2},"a":{"a":0,"k":[0,0],"ix":1},"s":{"a":0,"k":[100,100],"ix":3},"r":{"a":0,"k":0,"ix":6},"o":{"a":0,"k":100,"ix":7},"sk":{"a":0,"k":0,"ix":4},"sa":{"a":0,"k":0,"ix":5},"nm":"Transform","_render":true}],"nm":"Group 1","np":2,"cix":2,"bm":0,"ix":1,"mn":"ADBE Vector Group","hd":false,"_render":true},{"ty":"gr","it":[{"ind":0,"ty":"sh","ix":1,"ks":{"a":0,"k":{"i":[[73.837,128.5],[-55.903,128.5],[-88.376,113.96199999999999],[-88.376,-96.029],[-73.837,-128.5],[55.904,-128.5],[88.376,-113.96199999999999],[88.376,96.029]],"o":[[55.904,128.5],[-73.837,128.5],[-88.376,96.029],[-88.376,-113.96199999999999],[-55.903,-128.5],[73.837,-128.5],[88.376,-96.029],[88.376,113.96199999999999]],"v":[[55.904,128.5],[-55.903,128.5],[-88.376,96.029],[-88.376,-96.029],[-55.903,-128.5],[55.904,-128.5],[88.376,-96.029],[88.376,96.029]],"c":true},"ix":2},"nm":"Path 1","mn":"ADBE Vector Shape - Group","hd":false,"_render":true},{"ty":"st","c":{"a":0,"k":[0.945098099054,0.768627510819,0,1],"ix":3},"o":{"a":0,"k":100,"ix":4},"w":{"a":0,"k":16.253,"ix":5},"lc":1,"lj":1,"ml":10,"bm":0,"nm":"Stroke 1","mn":"ADBE Vector Graphic - Stroke","hd":false,"_render":true},{"ty":"fl","c":{"a":0,"k":[0.035294117647,0.125490196078,0.188235309077,1],"ix":4},"o":{"a":0,"k":100,"ix":5},"r":1,"bm":0,"nm":"Fill 1","mn":"ADBE Vector Graphic - Fill","hd":false,"_render":true},{"ty":"tr","p":{"a":0,"k":[129.008,169.132],"ix":2},"a":{"a":0,"k":[0,0],"ix":1},"s":{"a":0,"k":[100,100],"ix":3},"r":{"a":0,"k":0,"ix":6},"o":{"a":0,"k":100,"ix":7},"sk":{"a":0,"k":0,"ix":4},"sa":{"a":0,"k":0,"ix":5},"nm":"Transform","_render":true}],"nm":"Group 2","np":3,"cix":2,"bm":0,"ix":2,"mn":"ADBE Vector Group","hd":false,"_render":true}],"ip":19,"op":97,"st":0,"bm":0,"completed":true},{"ddd":0,"ind":8,"ty":4,"nm":"3 Outlines 2","parent":1,"sr":1,"ks":{"o":{"a":0,"k":100,"ix":11},"r":{"a":1,"k":[{"i":{"x":[0.591],"y":[4.941]},"o":{"x":[0.566],"y":[0]},"t":29,"s":[0]},{"i":{"x":[0.347],"y":[1]},"o":{"x":[0.923],"y":[0.115]},"t":34,"s":[-3]},{"t":42,"s":[337.5]}],"ix":10},"p":{"a":0,"k":[27,-72.539,0],"ix":2},"a":{"a":0,"k":[169.888,382.289,0],"ix":1},"s":{"a":0,"k":[100,100,100],"ix":6}},"ao":0,"shapes":[{"ty":"gr","it":[{"ind":0,"ty":"sh","ix":1,"ks":{"a":0,"k":{"i":[[17.269,-19.137],[17.624,-11.064],[14.306000000000001,-3.6959999999999997],[16.505000000000003,1.843],[20.912000000000003,8.534],[21.491,16.848],[19.047,24.535],[14.152000000000001,30.527],[7.245,34.161],[-0.7719999999999998,34.669],[-8.035,31.943],[-13.733,26.61],[-17.27,19.197999999999997],[-3.483,14.436],[-2.519,17.718],[1.253,20.536],[5.278,19.338],[7.321,14.784],[6.7,11.164000000000001],[5.372,8.348],[3.557,6.143999999999999],[1.4220000000000002,4.986000000000001],[-0.6,-4.525],[0.8079999999999999,-5.027],[2.3499999999999996,-7.294],[3.3030000000000004,-10.277],[3.596,-13.514],[2.513,-17.761],[-1.2009999999999998,-20.548000000000002],[-5.235,-19.36],[-7.342,-14.873000000000001],[-21.269,-11.182],[-21.491,-16.755],[-19.043,-24.443],[-14.151,-30.454],[-7.258000000000001,-34.161],[0.7650000000000001,-34.658],[8.034,-31.854000000000003],[13.733,-26.518]],"o":[[17.99,-13.661],[15.475,-5.981],[14.786999999999999,-0.04200000000000004],[19.889000000000003,6.14],[21.642000000000003,14.076],[20.14,22.151],[16.016,28.776],[9.711,33.289],[1.831,34.874],[-5.776999999999999,33.150999999999996],[-12.056000000000001,28.629],[-16.41,21.837],[-17.651,16.301],[-3.246,16.234],[-0.06999999999999984,20.05],[4.122999999999999,20.158],[7.0089999999999995,16.424],[6.966,12.087],[5.87,9.225000000000001],[4.203,6.778],[2.151,5.178999999999999],[0.665,5.086],[0.15700000000000003,-4.625],[1.899,-6.449],[3.056,-9.24],[3.5860000000000003,-12.488],[3.233,-16.273],[0.11399999999999988,-20.065],[-4.071,-20.17],[-7.016,-16.499],[-7.101,-13.047],[-21.642,-14.014],[-20.141000000000002,-22.058],[-16.017,-28.688000000000002],[-9.718,-33.278],[-1.8430000000000004,-34.874],[5.7780000000000005,-33.078],[12.06,-28.537000000000003],[16.41,-21.744999999999997]],"v":[[17.642,-16.305],[16.552,-8.523],[13.032,-1.671],[18.199,3.989],[21.26,11.178],[20.815,19.497],[17.532,26.657],[11.929,31.91],[4.54,34.517],[-3.272,33.912],[-10.044,30.288],[-15.068,24.221],[-17.651,16.301],[-3.483,14.436],[-1.295,18.882],[2.675,20.349],[6.145,17.879],[7.082,12.967],[6.287,10.194],[4.787,7.561],[2.856,5.661],[0.665,5.086],[-0.6,-4.525],[1.355,-5.74],[2.703,-8.267],[3.446,-11.383],[3.472,-14.455],[1.313,-18.913],[-2.638,-20.359],[-6.126,-17.93],[-7.101,-13.047],[-21.269,-11.182],[-20.812,-19.409],[-17.528,-26.565],[-11.932,-31.864],[-4.549,-34.517],[3.27,-33.866],[10.047,-30.196],[15.071,-24.133]],"c":true},"ix":2},"nm":"Path 1","mn":"ADBE Vector Shape - Group","hd":false,"_render":true},{"ty":"fl","c":{"a":0,"k":[0.945098099054,0.768627510819,0,1],"ix":4},"o":{"a":0,"k":100,"ix":5},"r":1,"bm":0,"nm":"Fill 1","mn":"ADBE Vector Graphic - Fill","hd":false,"_render":true},{"ty":"tr","p":{"a":0,"k":[143.126,175.851],"ix":2},"a":{"a":0,"k":[0,0],"ix":1},"s":{"a":0,"k":[100,100],"ix":3},"r":{"a":0,"k":0,"ix":6},"o":{"a":0,"k":100,"ix":7},"sk":{"a":0,"k":0,"ix":4},"sa":{"a":0,"k":0,"ix":5},"nm":"Transform","_render":true}],"nm":"Group 1","np":2,"cix":2,"bm":0,"ix":1,"mn":"ADBE Vector Group","hd":false,"_render":true},{"ty":"gr","it":[{"ind":0,"ty":"sh","ix":1,"ks":{"a":0,"k":{"i":[[89.978,117.762],[-38.654,134.697],[-72.745,124.522],[-100.154,-83.673],[-89.979,-117.764],[38.654,-134.698],[72.745,-124.523],[100.154,83.671]],"o":[[72.198,120.103],[-56.434000000000005,137.038],[-75.086,106.742],[-102.49499999999999,-101.453],[-72.199,-120.104],[56.434000000000005,-137.03900000000002],[75.086,-106.743],[102.49499999999999,101.45100000000001]],"v":[[72.198,120.103],[-38.654,134.697],[-75.086,106.742],[-100.154,-83.673],[-72.199,-120.104],[38.654,-134.698],[75.086,-106.743],[100.154,83.671]],"c":true},"ix":2},"nm":"Path 1","mn":"ADBE Vector Shape - Group","hd":false,"_render":true},{"ty":"st","c":{"a":0,"k":[0.945098099054,0.768627510819,0,1],"ix":3},"o":{"a":0,"k":100,"ix":4},"w":{"a":0,"k":16.253,"ix":5},"lc":1,"lj":1,"ml":10,"bm":0,"nm":"Stroke 1","mn":"ADBE Vector Graphic - Stroke","hd":false,"_render":true},{"ty":"fl","c":{"a":0,"k":[0.035294117647,0.125490196078,0.188235309077,1],"ix":4},"o":{"a":0,"k":100,"ix":5},"r":1,"bm":0,"nm":"Fill 1","mn":"ADBE Vector Graphic - Fill","hd":false,"_render":true},{"ty":"tr","p":{"a":0,"k":[143.127,177.671],"ix":2},"a":{"a":0,"k":[0,0],"ix":1},"s":{"a":0,"k":[100,100],"ix":3},"r":{"a":0,"k":0,"ix":6},"o":{"a":0,"k":100,"ix":7},"sk":{"a":0,"k":0,"ix":4},"sa":{"a":0,"k":0,"ix":5},"nm":"Transform","_render":true}],"nm":"Group 2","np":3,"cix":2,"bm":0,"ix":2,"mn":"ADBE Vector Group","hd":false,"_render":true}],"ip":39,"op":97,"st":0,"bm":0,"completed":true},{"ddd":0,"ind":9,"ty":4,"nm":"2 Outlines 2","parent":1,"sr":1,"ks":{"o":{"a":0,"k":100,"ix":11},"r":{"a":1,"k":[{"i":{"x":[0.591],"y":[4.941]},"o":{"x":[0.566],"y":[0]},"t":49,"s":[0]},{"i":{"x":[0.347],"y":[1]},"o":{"x":[0.923],"y":[0.112]},"t":54,"s":[-3]},{"t":62,"s":[345]}],"ix":10},"p":{"a":0,"k":[27.286,-73.203,0],"ix":2},"a":{"a":0,"k":[208.831,382.589,0],"ix":1},"s":{"a":0,"k":[100,100,100],"ix":6}},"ao":0,"shapes":[{"ty":"gr","it":[{"ind":0,"ty":"sh","ix":1,"ks":{"a":0,"k":{"i":[[0.748,16.528],[23.775,10.358],[27.553,24.459],[-19.067,36.95],[-22.845,22.85],[-22.562,22.774],[0.401,-6.948],[1.7939999999999998,-9.322],[2.2199999999999998,-13.683],[1.009,-17.453000000000003],[-1.068,-20.171],[-3.7049999999999996,-21.797],[-6.599,-22.198],[-9.450999999999999,-21.200000000000003],[-11.481,-19.061999999999998],[-12.634,-16.08],[-12.694,-12.572],[-12.199,-10.725],[-26.095,-6.198],[-26.472,-7.605],[-27.552999999999997,-13.828999999999999],[-25.964,-22.752],[-21.382,-30.157],[-14.366999999999999,-35.230000000000004],[-5.56,-36.949999999999996],[2.9110000000000005,-34.924],[10.07,-29.820999999999998],[15.078999999999999,-22.096],[17.066,-11.483],[14.096,-0.8130000000000002]],"o":[[0.748,16.528],[23.775,10.358],[27.553,24.459],[-19.067,36.95],[-22.845,22.85],[-22.562,22.774],[1.246,-8.048],[2.296,-12.206999999999999],[1.4989999999999999,-16.375],[-0.30700000000000005,-19.383000000000003],[-2.796,-21.389000000000003],[-5.622999999999999,-22.226],[-8.588000000000001,-21.665],[-10.895,-19.871000000000002],[-12.365,-17.144],[-12.809000000000001,-13.75],[-12.375,-11.383],[-12.199,-10.725],[-26.095,-6.198],[-27.311,-10.738],[-26.836,-19.932],[-23.187,-27.930999999999997],[-16.945,-33.899],[-8.472999999999999,-36.809000000000005],[0.2190000000000003,-35.945],[7.901,-31.825999999999997],[13.739,-24.893],[16.925,-15.203999999999999],[15.615,-4.11],[11.787,2.089]],"v":[[0.748,16.528],[23.775,10.358],[27.553,24.459],[-19.067,36.95],[-22.845,22.85],[-22.562,22.774],[0.401,-6.948],[2.046,-10.767],[1.817,-15.186],[0.352,-18.42],[-1.932,-20.78],[-4.664,-22.012],[-7.594,-21.932],[-10.171,-20.536],[-11.921,-18.104],[-12.72,-14.918],[-12.375,-11.383],[-12.199,-10.725],[-26.095,-6.198],[-26.472,-7.605],[-27.194,-16.88],[-24.576,-25.342],[-19.166,-32.03],[-11.418,-36.02],[-2.671,-36.449],[5.408,-33.376],[11.906,-27.357],[15.918,-18.964],[16.34,-7.796],[11.787,2.089]],"c":true},"ix":2},"nm":"Path 1","mn":"ADBE Vector Shape - Group","hd":false,"_render":true},{"ty":"fl","c":{"a":0,"k":[0.945098099054,0.768627510819,0,1],"ix":4},"o":{"a":0,"k":100,"ix":5},"r":1,"bm":0,"nm":"Fill 1","mn":"ADBE Vector Graphic - Fill","hd":false,"_render":true},{"ty":"tr","p":{"a":0,"k":[155.393,183.76],"ix":2},"a":{"a":0,"k":[0,0],"ix":1},"s":{"a":0,"k":[100,100],"ix":3},"r":{"a":0,"k":0,"ix":6},"o":{"a":0,"k":100,"ix":7},"sk":{"a":0,"k":0,"ix":4},"sa":{"a":0,"k":0,"ix":5},"nm":"Transform","_render":true}],"nm":"Group 1","np":2,"cix":2,"bm":0,"ix":1,"mn":"ADBE Vector Group","hd":false,"_render":true},{"ty":"gr","it":[{"ind":0,"ty":"sh","ix":1,"ks":{"a":0,"k":{"i":[[104.57900000000001,105.01],[-20.742,138.59],[-55.869,132.952],[-110.219,-69.884],[-104.58,-105.01100000000001],[20.742,-138.591],[55.867999999999995,-132.953],[110.219,69.883]],"o":[[87.257,109.652],[-38.064,143.232],[-60.511,115.629],[-114.86,-87.206],[-87.258,-109.653],[38.064,-143.232],[60.51,-115.63],[114.86,87.205]],"v":[[87.257,109.652],[-20.742,138.59],[-60.511,115.629],[-110.219,-69.884],[-87.258,-109.653],[20.742,-138.591],[60.51,-115.63],[110.219,69.883]],"c":true},"ix":2},"nm":"Path 1","mn":"ADBE Vector Shape - Group","hd":false,"_render":true},{"ty":"st","c":{"a":0,"k":[0.945098099054,0.768627510819,0,1],"ix":3},"o":{"a":0,"k":100,"ix":4},"w":{"a":0,"k":16.253,"ix":5},"lc":1,"lj":1,"ml":10,"bm":0,"nm":"Stroke 1","mn":"ADBE Vector Graphic - Stroke","hd":false,"_render":true},{"ty":"fl","c":{"a":0,"k":[0.035294117647,0.125490196078,0.188235309077,1],"ix":4},"o":{"a":0,"k":100,"ix":5},"r":1,"bm":0,"nm":"Fill 1","mn":"ADBE Vector Graphic - Fill","hd":false,"_render":true},{"ty":"tr","p":{"a":0,"k":[155.492,183.864],"ix":2},"a":{"a":0,"k":[0,0],"ix":1},"s":{"a":0,"k":[100,100],"ix":3},"r":{"a":0,"k":0,"ix":6},"o":{"a":0,"k":100,"ix":7},"sk":{"a":0,"k":0,"ix":4},"sa":{"a":0,"k":0,"ix":5},"nm":"Transform","_render":true}],"nm":"Group 2","np":3,"cix":2,"bm":0,"ix":2,"mn":"ADBE Vector Group","hd":false,"_render":true}],"ip":59,"op":97,"st":0,"bm":0,"completed":true},{"ddd":0,"ind":10,"ty":4,"nm":"1 Outlines 2","parent":1,"sr":1,"ks":{"o":{"a":0,"k":100,"ix":11},"r":{"a":1,"k":[{"i":{"x":[0.591],"y":[4.941]},"o":{"x":[0.566],"y":[0]},"t":69,"s":[0]},{"i":{"x":[0.347],"y":[1]},"o":{"x":[0.923],"y":[0.11]},"t":74,"s":[-3]},{"t":82,"s":[352.5]}],"ix":10},"p":{"a":0,"k":[27.351,-73.025,0],"ix":2},"a":{"a":0,"k":[244.682,377.894,0],"ix":1},"s":{"a":0,"k":[100,100,100],"ix":6}},"ao":0,"shapes":[{"ty":"gr","it":[{"ind":0,"ty":"sh","ix":1,"ks":{"a":0,"k":{"i":[[0.855,-35.183],[27.678,29.573],[14.132,35.183],[-6.667,-15.031],[-17.745,-4.729],[-27.678,-15.429],[-12.652,-29.48],[-12.69,-29.572]],"o":[[0.855,-35.183],[27.678,29.573],[14.132,35.183],[-6.667,-15.031],[-17.745,-4.729],[-27.678,-15.429],[-12.652,-29.48],[-12.69,-29.572]],"v":[[0.855,-35.183],[27.678,29.573],[14.132,35.183],[-6.667,-15.031],[-17.745,-4.729],[-27.678,-15.429],[-12.652,-29.48],[-12.69,-29.572]],"c":true},"ix":2},"nm":"Path 1","mn":"ADBE Vector Shape - Group","hd":false,"_render":true},{"ty":"fl","c":{"a":0,"k":[0.945098099054,0.768627510819,0,1],"ix":4},"o":{"a":0,"k":100,"ix":5},"r":1,"bm":0,"nm":"Fill 1","mn":"ADBE Vector Graphic - Fill","hd":false,"_render":true},{"ty":"tr","p":{"a":0,"k":[161.64,187.607],"ix":2},"a":{"a":0,"k":[0,0],"ix":1},"s":{"a":0,"k":[100,100],"ix":3},"r":{"a":0,"k":0,"ix":6},"o":{"a":0,"k":100,"ix":7},"sk":{"a":0,"k":0,"ix":4},"sa":{"a":0,"k":0,"ix":5},"nm":"Transform","_render":true}],"nm":"Group 1","np":2,"cix":2,"bm":0,"ix":1,"mn":"ADBE Vector Group","hd":false,"_render":true},{"ty":"gr","it":[{"ind":0,"ty":"sh","ix":1,"ks":{"a":0,"k":{"i":[[117.392,90.462],[-2.473,140.112],[-38.037,139.107],[-118.396,-54.899],[-117.39099999999999,-90.462],[2.474,-140.112],[38.037,-139.107],[118.397,54.899]],"o":[[100.824,97.325],[-19.041999999999998,146.975],[-44.9,122.539],[-125.259,-71.467],[-100.823,-97.325],[19.043,-146.975],[44.9,-122.539],[125.26,71.467]],"v":[[100.824,97.325],[-2.473,140.112],[-44.9,122.539],[-118.396,-54.899],[-100.823,-97.325],[2.474,-140.112],[44.9,-122.539],[118.397,54.899]],"c":true},"ix":2},"nm":"Path 1","mn":"ADBE Vector Shape - Group","hd":false,"_render":true},{"ty":"st","c":{"a":0,"k":[0.945098099054,0.768627510819,0,1],"ix":3},"o":{"a":0,"k":100,"ix":4},"w":{"a":0,"k":16.253,"ix":5},"lc":1,"lj":1,"ml":10,"bm":0,"nm":"Stroke 1","mn":"ADBE Vector Graphic - Stroke","hd":false,"_render":true},{"ty":"fl","c":{"a":0,"k":[0.035294117647,0.125490196078,0.188235309077,1],"ix":4},"o":{"a":0,"k":100,"ix":5},"r":1,"bm":0,"nm":"Fill 1","mn":"ADBE Vector Graphic - Fill","hd":false,"_render":true},{"ty":"tr","p":{"a":0,"k":[165.892,187.607],"ix":2},"a":{"a":0,"k":[0,0],"ix":1},"s":{"a":0,"k":[100,100],"ix":3},"r":{"a":0,"k":0,"ix":6},"o":{"a":0,"k":100,"ix":7},"sk":{"a":0,"k":0,"ix":4},"sa":{"a":0,"k":0,"ix":5},"nm":"Transform","_render":true}],"nm":"Group 2","np":3,"cix":2,"bm":0,"ix":2,"mn":"ADBE Vector Group","hd":false,"_render":true}],"ip":79,"op":97,"st":0,"bm":0,"completed":true}],"markers":[],"__complete":true}